aesfield/__init__.py
aesfield/default.py
aesfield/field.py
aesfield/models.py
aesfield/management/__init__.py
aesfield/management/commands/__init__.py
aesfield/management/commands/generate_aes_keys.py
aesfield/tests/__init__.py
aesfield/tests/sample.key
aesfield/tests/settings.py
aesfield/tests/test_basic.py
django_aesfield-4.0.0.dist-info/LICENSE.rst
django_aesfield-4.0.0.dist-info/METADATA
django_aesfield-4.0.0.dist-info/WHEEL
django_aesfield-4.0.0.dist-info/top_level.txt
django_aesfield-4.0.0.dist-info/RECORD
