Metadata-Version: 2.1
Name: django-aesfield
Version: 4.0.0
Summary: Django Model Field that supports AES encryption
Home-page: https://github.com/andymckay/django-aesfield
Author: Andy McKay
Author-email: andym@mozilla.com
Maintainer: Christopher Grebs
Maintainer-email: cg@webshox.org
License: BSD
Classifier: Development Status :: 5 - Production/Stable
Classifier: License :: OSI Approved :: BSD License
Classifier: Operating System :: OS Independent
Classifier: Intended Audience :: Developers
Classifier: Topic :: Software Development :: Libraries :: Python Modules
Classifier: Topic :: Security :: Cryptography
Classifier: Programming Language :: Python
Classifier: Programming Language :: Python :: 3
Classifier: Programming Language :: Python :: 3.8
Classifier: Programming Language :: Python :: 3.9
Classifier: Programming Language :: Python :: 3.10
Classifier: Programming Language :: Python :: Implementation :: CPython
Classifier: Framework :: Django
License-File: LICENSE.rst
Requires-Dist: Django (<5.0,>=3.2)
Requires-Dist: m2secret-py3 (>=1.3)
Provides-Extra: tests
Requires-Dist: pytest (==7.1.2) ; extra == 'tests'
Requires-Dist: pytest-django (==4.5.2) ; extra == 'tests'
